{
  "questions": [
    {
      "id": "61a1"
    }
  ],
  "users": [
    {
      "username": "Juanito",
      "password": "12345",
      "id": "fc0d"
    },
    {
      "id": "aec9",
      "username": "Pepe",
      "password": "1234"
    },
    {
      "id": "a0b9",
      "username": "Pepe",
      "password": "1234"
    },
    {
      "id": "258f",
      "username": "Mario",
      "password": "Coronado"
    },
    {
      "id": "7526",
      "username": "abc",
      "password": "1234"
    },
    {
      "id": "d23d",
      "username": "abc",
      "password": "1234"
    },
    {
      "id": "2247",
      "username": "abc",
      "password": "1234"
    }
  ]
}